{
  "id": "3040f783-bac6-470d-8e6a-1a8ca6bd82ab",
  "prevId": "d9ffa70d-2a82-4a79-be02-1822b60a4322",
  "version": "7",
  "dialect": "postgresql",
  "tables": {
    "public.calendar_connections": {
      "name": "calendar_connections",
      "schema": "",
      "columns": {
        "id": {
          "name": "id",
          "type": "uuid",
          "primaryKey": true,
          "notNull": true,
          "default": "gen_random_uuid()"
        },
        "track": {
          "name": "track",
          "type": "track",
          "typeSchema": "public",
          "primaryKey": false,
          "notNull": true
        },
        "google_account_email": {
          "name": "google_account_email",
          "type": "text",
          "primaryKey": false,
          "notNull": true
        },
        "google_calendar_id": {
          "name": "google_calendar_id",
          "type": "text",
          "primaryKey": false,
          "notNull": true
        },
        "access_token_encrypted": {
          "name": "access_token_encrypted",
          "type": "text",
          "primaryKey": false,
          "notNull": true
        },
        "refresh_token_encrypted": {
          "name": "refresh_token_encrypted",
          "type": "text",
          "primaryKey": false,
          "notNull": true
        },
        "token_expires_at": {
          "name": "token_expires_at",
          "type": "timestamp with time zone",
          "primaryKey": false,
          "notNull": true
        },
        "sync_token": {
          "name": "sync_token",
          "type": "text",
          "primaryKey": false,
          "notNull": false
        },
        "channel_id": {
          "name": "channel_id",
          "type": "text",
          "primaryKey": false,
          "notNull": false
        },
        "channel_resource_id": {
          "name": "channel_resource_id",
          "type": "text",
          "primaryKey": false,
          "notNull": false
        },
        "channel_expires_at": {
          "name": "channel_expires_at",
          "type": "timestamp with time zone",
          "primaryKey": false,
          "notNull": false
        },
        "channel_token": {
          "name": "channel_token",
          "type": "text",
          "primaryKey": false,
          "notNull": false
        },
        "status": {
          "name": "status",
          "type": "connection_status",
          "typeSchema": "public",
          "primaryKey": false,
          "notNull": true,
          "default": "'active'"
        },
        "last_synced_at": {
          "name": "last_synced_at",
          "type": "timestamp with time zone",
          "primaryKey": false,
          "notNull": false
        },
        "last_error": {
          "name": "last_error",
          "type": "text",
          "primaryKey": false,
          "notNull": false
        },
        "created_at": {
          "name": "created_at",
          "type": "timestamp with time zone",
          "primaryKey": false,
          "notNull": true,
          "default": "now()"
        },
        "updated_at": {
          "name": "updated_at",
          "type": "timestamp with time zone",
          "primaryKey": false,
          "notNull": true,
          "default": "now()"
        }
      },
      "indexes": {},
      "foreignKeys": {},
      "compositePrimaryKeys": {},
      "uniqueConstraints": {
        "calendar_connections_track_unique": {
          "name": "calendar_connections_track_unique",
          "nullsNotDistinct": false,
          "columns": [
            "track"
          ]
        }
      },
      "policies": {},
      "checkConstraints": {},
      "isRLSEnabled": false
    },
    "public.daily_log_items": {
      "name": "daily_log_items",
      "schema": "",
      "columns": {
        "id": {
          "name": "id",
          "type": "uuid",
          "primaryKey": true,
          "notNull": true,
          "default": "gen_random_uuid()"
        },
        "log_id": {
          "name": "log_id",
          "type": "uuid",
          "primaryKey": false,
          "notNull": true
        },
        "title": {
          "name": "title",
          "type": "text",
          "primaryKey": false,
          "notNull": true
        },
        "status": {
          "name": "status",
          "type": "daily_log_item_status",
          "typeSchema": "public",
          "primaryKey": false,
          "notNull": true,
          "default": "'planned'"
        },
        "rolled_over_to_id": {
          "name": "rolled_over_to_id",
          "type": "uuid",
          "primaryKey": false,
          "notNull": false
        },
        "position": {
          "name": "position",
          "type": "integer",
          "primaryKey": false,
          "notNull": true
        },
        "completed_at": {
          "name": "completed_at",
          "type": "timestamp with time zone",
          "primaryKey": false,
          "notNull": false
        },
        "created_at": {
          "name": "created_at",
          "type": "timestamp with time zone",
          "primaryKey": false,
          "notNull": true,
          "default": "now()"
        },
        "updated_at": {
          "name": "updated_at",
          "type": "timestamp with time zone",
          "primaryKey": false,
          "notNull": true,
          "default": "now()"
        }
      },
      "indexes": {
        "daily_log_items_log_id_idx": {
          "name": "daily_log_items_log_id_idx",
          "columns": [
            {
              "expression": "log_id",
              "isExpression": false,
              "asc": true,
              "nulls": "last"
            }
          ],
          "isUnique": false,
          "concurrently": false,
          "method": "btree",
          "with": {}
        }
      },
      "foreignKeys": {
        "daily_log_items_log_id_daily_logs_id_fk": {
          "name": "daily_log_items_log_id_daily_logs_id_fk",
          "tableFrom": "daily_log_items",
          "tableTo": "daily_logs",
          "columnsFrom": [
            "log_id"
          ],
          "columnsTo": [
            "id"
          ],
          "onDelete": "cascade",
          "onUpdate": "no action"
        },
        "daily_log_items_rolled_over_to_id_fk": {
          "name": "daily_log_items_rolled_over_to_id_fk",
          "tableFrom": "daily_log_items",
          "tableTo": "daily_log_items",
          "columnsFrom": [
            "rolled_over_to_id"
          ],
          "columnsTo": [
            "id"
          ],
          "onDelete": "set null",
          "onUpdate": "no action"
        }
      },
      "compositePrimaryKeys": {},
      "uniqueConstraints": {},
      "policies": {},
      "checkConstraints": {},
      "isRLSEnabled": false
    },
    "public.daily_logs": {
      "name": "daily_logs",
      "schema": "",
      "columns": {
        "id": {
          "name": "id",
          "type": "uuid",
          "primaryKey": true,
          "notNull": true,
          "default": "gen_random_uuid()"
        },
        "log_date": {
          "name": "log_date",
          "type": "date",
          "primaryKey": false,
          "notNull": true
        },
        "retro": {
          "name": "retro",
          "type": "text",
          "primaryKey": false,
          "notNull": false
        },
        "mood": {
          "name": "mood",
          "type": "smallint",
          "primaryKey": false,
          "notNull": false
        },
        "created_at": {
          "name": "created_at",
          "type": "timestamp with time zone",
          "primaryKey": false,
          "notNull": true,
          "default": "now()"
        },
        "updated_at": {
          "name": "updated_at",
          "type": "timestamp with time zone",
          "primaryKey": false,
          "notNull": true,
          "default": "now()"
        }
      },
      "indexes": {},
      "foreignKeys": {},
      "compositePrimaryKeys": {},
      "uniqueConstraints": {
        "daily_logs_log_date_unique": {
          "name": "daily_logs_log_date_unique",
          "nullsNotDistinct": false,
          "columns": [
            "log_date"
          ]
        }
      },
      "policies": {},
      "checkConstraints": {
        "daily_logs_mood_range": {
          "name": "daily_logs_mood_range",
          "value": "\"daily_logs\".\"mood\" is null or (\"daily_logs\".\"mood\" >= 1 and \"daily_logs\".\"mood\" <= 5)"
        }
      },
      "isRLSEnabled": false
    },
    "public.event_sync_links": {
      "name": "event_sync_links",
      "schema": "",
      "columns": {
        "id": {
          "name": "id",
          "type": "uuid",
          "primaryKey": true,
          "notNull": true,
          "default": "gen_random_uuid()"
        },
        "event_id": {
          "name": "event_id",
          "type": "uuid",
          "primaryKey": false,
          "notNull": false
        },
        "connection_id": {
          "name": "connection_id",
          "type": "uuid",
          "primaryKey": false,
          "notNull": false
        },
        "google_event_id": {
          "name": "google_event_id",
          "type": "text",
          "primaryKey": false,
          "notNull": false
        },
        "google_etag": {
          "name": "google_etag",
          "type": "text",
          "primaryKey": false,
          "notNull": false
        },
        "google_updated_at": {
          "name": "google_updated_at",
          "type": "timestamp with time zone",
          "primaryKey": false,
          "notNull": false
        },
        "push_state": {
          "name": "push_state",
          "type": "push_state",
          "typeSchema": "public",
          "primaryKey": false,
          "notNull": true,
          "default": "'synced'"
        },
        "conflict_note": {
          "name": "conflict_note",
          "type": "text",
          "primaryKey": false,
          "notNull": false
        },
        "created_at": {
          "name": "created_at",
          "type": "timestamp with time zone",
          "primaryKey": false,
          "notNull": true,
          "default": "now()"
        },
        "updated_at": {
          "name": "updated_at",
          "type": "timestamp with time zone",
          "primaryKey": false,
          "notNull": true,
          "default": "now()"
        }
      },
      "indexes": {
        "event_sync_links_connection_id_idx": {
          "name": "event_sync_links_connection_id_idx",
          "columns": [
            {
              "expression": "connection_id",
              "isExpression": false,
              "asc": true,
              "nulls": "last"
            }
          ],
          "isUnique": false,
          "concurrently": false,
          "method": "btree",
          "with": {}
        },
        "event_sync_links_google_event_id_idx": {
          "name": "event_sync_links_google_event_id_idx",
          "columns": [
            {
              "expression": "google_event_id",
              "isExpression": false,
              "asc": true,
              "nulls": "last"
            }
          ],
          "isUnique": false,
          "concurrently": false,
          "method": "btree",
          "with": {}
        }
      },
      "foreignKeys": {
        "event_sync_links_event_id_events_id_fk": {
          "name": "event_sync_links_event_id_events_id_fk",
          "tableFrom": "event_sync_links",
          "tableTo": "events",
          "columnsFrom": [
            "event_id"
          ],
          "columnsTo": [
            "id"
          ],
          "onDelete": "set null",
          "onUpdate": "no action"
        },
        "event_sync_links_connection_id_calendar_connections_id_fk": {
          "name": "event_sync_links_connection_id_calendar_connections_id_fk",
          "tableFrom": "event_sync_links",
          "tableTo": "calendar_connections",
          "columnsFrom": [
            "connection_id"
          ],
          "columnsTo": [
            "id"
          ],
          "onDelete": "set null",
          "onUpdate": "no action"
        }
      },
      "compositePrimaryKeys": {},
      "uniqueConstraints": {
        "event_sync_links_event_id_unique": {
          "name": "event_sync_links_event_id_unique",
          "nullsNotDistinct": false,
          "columns": [
            "event_id"
          ]
        }
      },
      "policies": {},
      "checkConstraints": {},
      "isRLSEnabled": false
    },
    "public.events": {
      "name": "events",
      "schema": "",
      "columns": {
        "id": {
          "name": "id",
          "type": "uuid",
          "primaryKey": true,
          "notNull": true,
          "default": "gen_random_uuid()"
        },
        "track": {
          "name": "track",
          "type": "track",
          "typeSchema": "public",
          "primaryKey": false,
          "notNull": true
        },
        "title": {
          "name": "title",
          "type": "text",
          "primaryKey": false,
          "notNull": true
        },
        "description": {
          "name": "description",
          "type": "text",
          "primaryKey": false,
          "notNull": false
        },
        "starts_at": {
          "name": "starts_at",
          "type": "timestamp with time zone",
          "primaryKey": false,
          "notNull": true
        },
        "ends_at": {
          "name": "ends_at",
          "type": "timestamp with time zone",
          "primaryKey": false,
          "notNull": true
        },
        "all_day": {
          "name": "all_day",
          "type": "boolean",
          "primaryKey": false,
          "notNull": true,
          "default": false
        },
        "created_at": {
          "name": "created_at",
          "type": "timestamp with time zone",
          "primaryKey": false,
          "notNull": true,
          "default": "now()"
        },
        "updated_at": {
          "name": "updated_at",
          "type": "timestamp with time zone",
          "primaryKey": false,
          "notNull": true,
          "default": "now()"
        }
      },
      "indexes": {
        "events_starts_at_ends_at_idx": {
          "name": "events_starts_at_ends_at_idx",
          "columns": [
            {
              "expression": "starts_at",
              "isExpression": false,
              "asc": true,
              "nulls": "last"
            },
            {
              "expression": "ends_at",
              "isExpression": false,
              "asc": true,
              "nulls": "last"
            }
          ],
          "isUnique": false,
          "concurrently": false,
          "method": "btree",
          "with": {}
        }
      },
      "foreignKeys": {},
      "compositePrimaryKeys": {},
      "uniqueConstraints": {
        "events_id_track_unique": {
          "name": "events_id_track_unique",
          "nullsNotDistinct": false,
          "columns": [
            "id",
            "track"
          ]
        }
      },
      "policies": {},
      "checkConstraints": {
        "events_ends_at_after_starts_at": {
          "name": "events_ends_at_after_starts_at",
          "value": "\"events\".\"ends_at\" >= \"events\".\"starts_at\""
        }
      },
      "isRLSEnabled": false
    },
    "public.idea_checklist_items": {
      "name": "idea_checklist_items",
      "schema": "",
      "columns": {
        "id": {
          "name": "id",
          "type": "uuid",
          "primaryKey": true,
          "notNull": true,
          "default": "gen_random_uuid()"
        },
        "idea_id": {
          "name": "idea_id",
          "type": "uuid",
          "primaryKey": false,
          "notNull": true
        },
        "label": {
          "name": "label",
          "type": "text",
          "primaryKey": false,
          "notNull": true
        },
        "done": {
          "name": "done",
          "type": "boolean",
          "primaryKey": false,
          "notNull": true,
          "default": false
        },
        "position": {
          "name": "position",
          "type": "integer",
          "primaryKey": false,
          "notNull": true
        },
        "created_at": {
          "name": "created_at",
          "type": "timestamp with time zone",
          "primaryKey": false,
          "notNull": true,
          "default": "now()"
        },
        "updated_at": {
          "name": "updated_at",
          "type": "timestamp with time zone",
          "primaryKey": false,
          "notNull": true,
          "default": "now()"
        }
      },
      "indexes": {
        "idea_checklist_items_idea_id_idx": {
          "name": "idea_checklist_items_idea_id_idx",
          "columns": [
            {
              "expression": "idea_id",
              "isExpression": false,
              "asc": true,
              "nulls": "last"
            }
          ],
          "isUnique": false,
          "concurrently": false,
          "method": "btree",
          "with": {}
        }
      },
      "foreignKeys": {
        "idea_checklist_items_idea_id_ideas_id_fk": {
          "name": "idea_checklist_items_idea_id_ideas_id_fk",
          "tableFrom": "idea_checklist_items",
          "tableTo": "ideas",
          "columnsFrom": [
            "idea_id"
          ],
          "columnsTo": [
            "id"
          ],
          "onDelete": "cascade",
          "onUpdate": "no action"
        }
      },
      "compositePrimaryKeys": {},
      "uniqueConstraints": {},
      "policies": {},
      "checkConstraints": {},
      "isRLSEnabled": false
    },
    "public.idea_event_links": {
      "name": "idea_event_links",
      "schema": "",
      "columns": {
        "idea_id": {
          "name": "idea_id",
          "type": "uuid",
          "primaryKey": false,
          "notNull": true
        },
        "event_id": {
          "name": "event_id",
          "type": "uuid",
          "primaryKey": false,
          "notNull": true
        },
        "event_track": {
          "name": "event_track",
          "type": "track",
          "typeSchema": "public",
          "primaryKey": false,
          "notNull": true
        },
        "created_at": {
          "name": "created_at",
          "type": "timestamp with time zone",
          "primaryKey": false,
          "notNull": true,
          "default": "now()"
        }
      },
      "indexes": {},
      "foreignKeys": {
        "idea_event_links_idea_id_ideas_id_fk": {
          "name": "idea_event_links_idea_id_ideas_id_fk",
          "tableFrom": "idea_event_links",
          "tableTo": "ideas",
          "columnsFrom": [
            "idea_id"
          ],
          "columnsTo": [
            "id"
          ],
          "onDelete": "cascade",
          "onUpdate": "no action"
        },
        "idea_event_links_event_id_event_track_fk": {
          "name": "idea_event_links_event_id_event_track_fk",
          "tableFrom": "idea_event_links",
          "tableTo": "events",
          "columnsFrom": [
            "event_id",
            "event_track"
          ],
          "columnsTo": [
            "id",
            "track"
          ],
          "onDelete": "cascade",
          "onUpdate": "no action"
        }
      },
      "compositePrimaryKeys": {
        "idea_event_links_idea_id_event_id_pk": {
          "name": "idea_event_links_idea_id_event_id_pk",
          "columns": [
            "idea_id",
            "event_id"
          ]
        }
      },
      "uniqueConstraints": {},
      "policies": {},
      "checkConstraints": {
        "idea_event_links_event_track_content": {
          "name": "idea_event_links_event_track_content",
          "value": "\"idea_event_links\".\"event_track\" = 'content'"
        }
      },
      "isRLSEnabled": false
    },
    "public.ideas": {
      "name": "ideas",
      "schema": "",
      "columns": {
        "id": {
          "name": "id",
          "type": "uuid",
          "primaryKey": true,
          "notNull": true,
          "default": "gen_random_uuid()"
        },
        "title": {
          "name": "title",
          "type": "text",
          "primaryKey": false,
          "notNull": true
        },
        "notes": {
          "name": "notes",
          "type": "text",
          "primaryKey": false,
          "notNull": false
        },
        "format": {
          "name": "format",
          "type": "idea_format",
          "typeSchema": "public",
          "primaryKey": false,
          "notNull": true,
          "default": "'either'"
        },
        "status": {
          "name": "status",
          "type": "idea_status",
          "typeSchema": "public",
          "primaryKey": false,
          "notNull": true,
          "default": "'spark'"
        },
        "tags": {
          "name": "tags",
          "type": "text[]",
          "primaryKey": false,
          "notNull": true,
          "default": "'{}'"
        },
        "project_id": {
          "name": "project_id",
          "type": "uuid",
          "primaryKey": false,
          "notNull": false
        },
        "stage_entered_at": {
          "name": "stage_entered_at",
          "type": "timestamp with time zone",
          "primaryKey": false,
          "notNull": true,
          "default": "now()"
        },
        "created_at": {
          "name": "created_at",
          "type": "timestamp with time zone",
          "primaryKey": false,
          "notNull": true,
          "default": "now()"
        },
        "updated_at": {
          "name": "updated_at",
          "type": "timestamp with time zone",
          "primaryKey": false,
          "notNull": true,
          "default": "now()"
        }
      },
      "indexes": {
        "ideas_status_idx": {
          "name": "ideas_status_idx",
          "columns": [
            {
              "expression": "status",
              "isExpression": false,
              "asc": true,
              "nulls": "last"
            }
          ],
          "isUnique": false,
          "concurrently": false,
          "method": "btree",
          "with": {}
        },
        "ideas_created_at_idx": {
          "name": "ideas_created_at_idx",
          "columns": [
            {
              "expression": "created_at",
              "isExpression": false,
              "asc": true,
              "nulls": "last"
            }
          ],
          "isUnique": false,
          "concurrently": false,
          "method": "btree",
          "with": {}
        },
        "ideas_tags_idx": {
          "name": "ideas_tags_idx",
          "columns": [
            {
              "expression": "tags",
              "isExpression": false,
              "asc": true,
              "nulls": "last"
            }
          ],
          "isUnique": false,
          "concurrently": false,
          "method": "gin",
          "with": {}
        },
        "ideas_stage_entered_at_idx": {
          "name": "ideas_stage_entered_at_idx",
          "columns": [
            {
              "expression": "stage_entered_at",
              "isExpression": false,
              "asc": true,
              "nulls": "last"
            }
          ],
          "isUnique": false,
          "concurrently": false,
          "method": "btree",
          "with": {}
        }
      },
      "foreignKeys": {},
      "compositePrimaryKeys": {},
      "uniqueConstraints": {},
      "policies": {},
      "checkConstraints": {},
      "isRLSEnabled": false
    },
    "public.scripts": {
      "name": "scripts",
      "schema": "",
      "columns": {
        "id": {
          "name": "id",
          "type": "uuid",
          "primaryKey": true,
          "notNull": true,
          "default": "gen_random_uuid()"
        },
        "idea_id": {
          "name": "idea_id",
          "type": "uuid",
          "primaryKey": false,
          "notNull": true
        },
        "content": {
          "name": "content",
          "type": "text",
          "primaryKey": false,
          "notNull": true,
          "default": "''"
        },
        "created_at": {
          "name": "created_at",
          "type": "timestamp with time zone",
          "primaryKey": false,
          "notNull": true,
          "default": "now()"
        },
        "updated_at": {
          "name": "updated_at",
          "type": "timestamp with time zone",
          "primaryKey": false,
          "notNull": true,
          "default": "now()"
        }
      },
      "indexes": {},
      "foreignKeys": {
        "scripts_idea_id_ideas_id_fk": {
          "name": "scripts_idea_id_ideas_id_fk",
          "tableFrom": "scripts",
          "tableTo": "ideas",
          "columnsFrom": [
            "idea_id"
          ],
          "columnsTo": [
            "id"
          ],
          "onDelete": "cascade",
          "onUpdate": "no action"
        }
      },
      "compositePrimaryKeys": {},
      "uniqueConstraints": {
        "scripts_idea_id_unique": {
          "name": "scripts_idea_id_unique",
          "nullsNotDistinct": false,
          "columns": [
            "idea_id"
          ]
        }
      },
      "policies": {},
      "checkConstraints": {},
      "isRLSEnabled": false
    },
    "public.stream_checklist_items": {
      "name": "stream_checklist_items",
      "schema": "",
      "columns": {
        "id": {
          "name": "id",
          "type": "uuid",
          "primaryKey": true,
          "notNull": true,
          "default": "gen_random_uuid()"
        },
        "stream_id": {
          "name": "stream_id",
          "type": "uuid",
          "primaryKey": false,
          "notNull": true
        },
        "label": {
          "name": "label",
          "type": "text",
          "primaryKey": false,
          "notNull": true
        },
        "done": {
          "name": "done",
          "type": "boolean",
          "primaryKey": false,
          "notNull": true,
          "default": false
        },
        "position": {
          "name": "position",
          "type": "integer",
          "primaryKey": false,
          "notNull": true
        },
        "created_at": {
          "name": "created_at",
          "type": "timestamp with time zone",
          "primaryKey": false,
          "notNull": true,
          "default": "now()"
        },
        "updated_at": {
          "name": "updated_at",
          "type": "timestamp with time zone",
          "primaryKey": false,
          "notNull": true,
          "default": "now()"
        }
      },
      "indexes": {
        "stream_checklist_items_stream_id_idx": {
          "name": "stream_checklist_items_stream_id_idx",
          "columns": [
            {
              "expression": "stream_id",
              "isExpression": false,
              "asc": true,
              "nulls": "last"
            }
          ],
          "isUnique": false,
          "concurrently": false,
          "method": "btree",
          "with": {}
        }
      },
      "foreignKeys": {
        "stream_checklist_items_stream_id_streams_id_fk": {
          "name": "stream_checklist_items_stream_id_streams_id_fk",
          "tableFrom": "stream_checklist_items",
          "tableTo": "streams",
          "columnsFrom": [
            "stream_id"
          ],
          "columnsTo": [
            "id"
          ],
          "onDelete": "cascade",
          "onUpdate": "no action"
        }
      },
      "compositePrimaryKeys": {},
      "uniqueConstraints": {},
      "policies": {},
      "checkConstraints": {},
      "isRLSEnabled": false
    },
    "public.stream_checklist_template_items": {
      "name": "stream_checklist_template_items",
      "schema": "",
      "columns": {
        "id": {
          "name": "id",
          "type": "uuid",
          "primaryKey": true,
          "notNull": true,
          "default": "gen_random_uuid()"
        },
        "label": {
          "name": "label",
          "type": "text",
          "primaryKey": false,
          "notNull": true
        },
        "position": {
          "name": "position",
          "type": "integer",
          "primaryKey": false,
          "notNull": true
        },
        "created_at": {
          "name": "created_at",
          "type": "timestamp with time zone",
          "primaryKey": false,
          "notNull": true,
          "default": "now()"
        },
        "updated_at": {
          "name": "updated_at",
          "type": "timestamp with time zone",
          "primaryKey": false,
          "notNull": true,
          "default": "now()"
        }
      },
      "indexes": {
        "stream_checklist_template_items_position_idx": {
          "name": "stream_checklist_template_items_position_idx",
          "columns": [
            {
              "expression": "position",
              "isExpression": false,
              "asc": true,
              "nulls": "last"
            }
          ],
          "isUnique": false,
          "concurrently": false,
          "method": "btree",
          "with": {}
        }
      },
      "foreignKeys": {},
      "compositePrimaryKeys": {},
      "uniqueConstraints": {},
      "policies": {},
      "checkConstraints": {},
      "isRLSEnabled": false
    },
    "public.streams": {
      "name": "streams",
      "schema": "",
      "columns": {
        "id": {
          "name": "id",
          "type": "uuid",
          "primaryKey": true,
          "notNull": true,
          "default": "gen_random_uuid()"
        },
        "title": {
          "name": "title",
          "type": "text",
          "primaryKey": false,
          "notNull": true
        },
        "notes": {
          "name": "notes",
          "type": "text",
          "primaryKey": false,
          "notNull": false
        },
        "retro_notes": {
          "name": "retro_notes",
          "type": "text",
          "primaryKey": false,
          "notNull": false
        },
        "event_id": {
          "name": "event_id",
          "type": "uuid",
          "primaryKey": false,
          "notNull": false
        },
        "event_track": {
          "name": "event_track",
          "type": "track",
          "typeSchema": "public",
          "primaryKey": false,
          "notNull": false
        },
        "created_at": {
          "name": "created_at",
          "type": "timestamp with time zone",
          "primaryKey": false,
          "notNull": true,
          "default": "now()"
        },
        "updated_at": {
          "name": "updated_at",
          "type": "timestamp with time zone",
          "primaryKey": false,
          "notNull": true,
          "default": "now()"
        }
      },
      "indexes": {},
      "foreignKeys": {
        "streams_event_id_event_track_fk": {
          "name": "streams_event_id_event_track_fk",
          "tableFrom": "streams",
          "tableTo": "events",
          "columnsFrom": [
            "event_id",
            "event_track"
          ],
          "columnsTo": [
            "id",
            "track"
          ],
          "onDelete": "set null",
          "onUpdate": "no action"
        }
      },
      "compositePrimaryKeys": {},
      "uniqueConstraints": {
        "streams_event_id_unique": {
          "name": "streams_event_id_unique",
          "nullsNotDistinct": false,
          "columns": [
            "event_id"
          ]
        }
      },
      "policies": {},
      "checkConstraints": {
        "streams_event_track_content": {
          "name": "streams_event_track_content",
          "value": "\"streams\".\"event_track\" is null or \"streams\".\"event_track\" = 'content'"
        }
      },
      "isRLSEnabled": false
    },
    "public.weekly_reviews": {
      "name": "weekly_reviews",
      "schema": "",
      "columns": {
        "id": {
          "name": "id",
          "type": "uuid",
          "primaryKey": true,
          "notNull": true,
          "default": "gen_random_uuid()"
        },
        "week_start": {
          "name": "week_start",
          "type": "date",
          "primaryKey": false,
          "notNull": true
        },
        "highlights": {
          "name": "highlights",
          "type": "text",
          "primaryKey": false,
          "notNull": false
        },
        "created_at": {
          "name": "created_at",
          "type": "timestamp with time zone",
          "primaryKey": false,
          "notNull": true,
          "default": "now()"
        },
        "updated_at": {
          "name": "updated_at",
          "type": "timestamp with time zone",
          "primaryKey": false,
          "notNull": true,
          "default": "now()"
        }
      },
      "indexes": {},
      "foreignKeys": {},
      "compositePrimaryKeys": {},
      "uniqueConstraints": {
        "weekly_reviews_week_start_unique": {
          "name": "weekly_reviews_week_start_unique",
          "nullsNotDistinct": false,
          "columns": [
            "week_start"
          ]
        }
      },
      "policies": {},
      "checkConstraints": {},
      "isRLSEnabled": false
    }
  },
  "enums": {
    "public.connection_status": {
      "name": "connection_status",
      "schema": "public",
      "values": [
        "active",
        "error",
        "disconnected"
      ]
    },
    "public.daily_log_item_status": {
      "name": "daily_log_item_status",
      "schema": "public",
      "values": [
        "planned",
        "done",
        "rolled_over"
      ]
    },
    "public.idea_format": {
      "name": "idea_format",
      "schema": "public",
      "values": [
        "video",
        "stream",
        "either"
      ]
    },
    "public.idea_status": {
      "name": "idea_status",
      "schema": "public",
      "values": [
        "spark",
        "outlined",
        "scripted",
        "recorded",
        "edited",
        "published",
        "parked"
      ]
    },
    "public.push_state": {
      "name": "push_state",
      "schema": "public",
      "values": [
        "synced",
        "pending_push",
        "pending_delete",
        "error"
      ]
    },
    "public.track": {
      "name": "track",
      "schema": "public",
      "values": [
        "work",
        "content"
      ]
    }
  },
  "schemas": {},
  "sequences": {},
  "roles": {},
  "policies": {},
  "views": {},
  "_meta": {
    "columns": {},
    "schemas": {},
    "tables": {}
  }
}